kevinbotlib/__about__.py
kevinbotlib/__init__.py
kevinbotlib/core.py
kevinbotlib/exceptions.py
kevinbotlib/launch.py
kevinbotlib/py.typed
kevinbotlib/states.py
kevinbotlib-0.0.1.dist-info/METADATA
kevinbotlib-0.0.1.dist-info/WHEEL
kevinbotlib-0.0.1.dist-info/entry_points.txt
kevinbotlib-0.0.1.dist-info/licenses/LICENSE.txt
kevinbotlib-0.0.1.dist-info/RECORD
